{"textures":[{"image":"effects-resources.png","format":"RGBA8888","size":{"w":797,"h":128},"scale":1,"frames":[{"filename":"blank","rotated":false,"trimmed":false,"sourceSize":{"w":100,"h":100},"spriteSourceSize":{"x":0,"y":0,"w":100,"h":100},"frame":{"x":2,"y":2,"w":100,"h":100}},{"filename":"confetti/star-x/star-1","rotated":false,"trimmed":false,"sourceSize":{"w":21,"h":20},"spriteSourceSize":{"x":0,"y":0,"w":21,"h":20},"frame":{"x":2,"y":105,"w":21,"h":20}},{"filename":"confetti/star-y/star-1","rotated":false,"trimmed":false,"sourceSize":{"w":21,"h":20},"spriteSourceSize":{"x":0,"y":0,"w":21,"h":20},"frame":{"x":2,"y":105,"w":21,"h":20}},{"filename":"star-x/star-1","rotated":false,"trimmed":false,"sourceSize":{"w":21,"h":20},"spriteSourceSize":{"x":0,"y":0,"w":21,"h":20},"frame":{"x":2,"y":105,"w":21,"h":20}},{"filename":"star-y/star-1","rotated":false,"trimmed":false,"sourceSize":{"w":21,"h":20},"spriteSourceSize":{"x":0,"y":0,"w":21,"h":20},"frame":{"x":2,"y":105,"w":21,"h":20}},{"filename":"confetti/star-y/star-4","rotated":false,"trimmed":true,"sourceSize":{"w":21,"h":20},"spriteSourceSize":{"x":2,"y":0,"w":18,"h":20},"frame":{"x":26,"y":105,"w":18,"h":20}},{"filename":"star-y/star-4","rotated":false,"trimmed":true,"sourceSize":{"w":21,"h":20},"spriteSourceSize":{"x":2,"y":0,"w":18,"h":20},"frame":{"x":26,"y":105,"w":18,"h":20}},{"filename":"confetti/star-y/star-2","rotated":false,"trimmed":true,"sourceSize":{"w":21,"h":20},"spriteSourceSize":{"x":5,"y":1,"w":13,"h":19},"frame":{"x":47,"y":105,"w":13,"h":19}},{"filename":"star-y/star-2","rotated":false,"trimmed":true,"sourceSize":{"w":21,"h":20},"spriteSourceSize":{"x":5,"y":1,"w":13,"h":19},"frame":{"x":47,"y":105,"w":13,"h":19}},{"filename":"confetti/star-y/star-3","rotated":false,"trimmed":true,"sourceSize":{"w":21,"h":20},"spriteSourceSize":{"x":8,"y":1,"w":6,"h":19},"frame":{"x":63,"y":105,"w":6,"h":19}},{"filename":"star-y/star-3","rotated":false,"trimmed":true,"sourceSize":{"w":21,"h":20},"spriteSourceSize":{"x":8,"y":1,"w":6,"h":19},"frame":{"x":63,"y":105,"w":6,"h":19}},{"filename":"ribbon/falling-confetti/confetti-c/confetti-c-1","rotated":false,"trimmed":false,"sourceSize":{"w":24,"h":16},"spriteSourceSize":{"x":0,"y":0,"w":24,"h":16},"frame":{"x":72,"y":105,"w":24,"h":16}},{"filename":"ribbon","rotated":false,"trimmed":false,"sourceSize":{"w":64,"h":2},"spriteSourceSize":{"x":0,"y":0,"w":64,"h":2},"frame":{"x":72,"y":124,"w":64,"h":2}},{"filename":"confetti/star-x/star-2","rotated":false,"trimmed":true,"sourceSize":{"w":21,"h":20},"spriteSourceSize":{"x":1,"y":2,"w":20,"h":16},"frame":{"x":99,"y":105,"w":20,"h":16}},{"filename":"star-x/star-2","rotated":false,"trimmed":true,"sourceSize":{"w":21,"h":20},"spriteSourceSize":{"x":1,"y":2,"w":20,"h":16},"frame":{"x":99,"y":105,"w":20,"h":16}},{"filename":"star","rotated":false,"trimmed":true,"sourceSize":{"w":100,"h":100},"spriteSourceSize":{"x":2,"y":2,"w":96,"h":96},"frame":{"x":105,"y":2,"w":96,"h":96}},{"filename":"confetti/small-3","rotated":false,"trimmed":false,"sourceSize":{"w":16,"h":24},"spriteSourceSize":{"x":0,"y":0,"w":16,"h":24},"frame":{"x":139,"y":101,"w":16,"h":24}},{"filename":"confetti/small-2","rotated":false,"trimmed":false,"sourceSize":{"w":22,"h":23},"spriteSourceSize":{"x":0,"y":0,"w":22,"h":23},"frame":{"x":158,"y":101,"w":22,"h":23}},{"filename":"ribbon/falling-confetti/confetti-b/confetti-b-1","rotated":false,"trimmed":false,"sourceSize":{"w":23,"h":14},"spriteSourceSize":{"x":0,"y":0,"w":23,"h":14},"frame":{"x":183,"y":101,"w":23,"h":14}},{"filename":"ribbon/falling-confetti/confetti-c/confetti-c-3","rotated":false,"trimmed":false,"sourceSize":{"w":23,"h":7},"spriteSourceSize":{"x":0,"y":0,"w":23,"h":7},"frame":{"x":183,"y":118,"w":23,"h":7}},{"filename":"text/text_excellent","rotated":false,"trimmed":false,"sourceSize":{"w":518,"h":57},"spriteSourceSize":{"x":0,"y":0,"w":518,"h":57},"frame":{"x":204,"y":2,"w":518,"h":57}},{"filename":"confetti/hexagon-3","rotated":false,"trimmed":true,"sourceSize":{"w":50,"h":50},"spriteSourceSize":{"x":9,"y":8,"w":34,"h":34},"frame":{"x":204,"y":62,"w":34,"h":34}},{"filename":"confetti/small-4","rotated":false,"trimmed":true,"sourceSize":{"w":28,"h":31},"spriteSourceSize":{"x":5,"y":3,"w":18,"h":26},"frame":{"x":209,"y":99,"w":18,"h":26}},{"filename":"text/text_cool","rotated":false,"trimmed":false,"sourceSize":{"w":257,"h":56},"spriteSourceSize":{"x":0,"y":0,"w":257,"h":56},"frame":{"x":241,"y":62,"w":257,"h":56}},{"filename":"ribbon/falling-confetti/confetti-b/confetti-b-3","rotated":false,"trimmed":false,"sourceSize":{"w":25,"h":5},"spriteSourceSize":{"x":0,"y":0,"w":25,"h":5},"frame":{"x":230,"y":121,"w":25,"h":5}},{"filename":"ribbon/falling-confetti/confetti-d/confetti-d-4","rotated":false,"trimmed":false,"sourceSize":{"w":23,"h":4},"spriteSourceSize":{"x":0,"y":0,"w":23,"h":4},"frame":{"x":258,"y":121,"w":23,"h":4}},{"filename":"ribbon/falling-confetti/confetti-a/confetti-a-3","rotated":false,"trimmed":false,"sourceSize":{"w":21,"h":3},"spriteSourceSize":{"x":0,"y":0,"w":21,"h":3},"frame":{"x":284,"y":121,"w":21,"h":3}},{"filename":"ribbon/falling-confetti/confetti-b/confetti-b-4","rotated":false,"trimmed":false,"sourceSize":{"w":26,"h":2},"spriteSourceSize":{"x":0,"y":0,"w":26,"h":2},"frame":{"x":308,"y":121,"w":26,"h":2}},{"filename":"text/text_good","rotated":false,"trimmed":false,"sourceSize":{"w":145,"h":56},"spriteSourceSize":{"x":0,"y":0,"w":145,"h":56},"frame":{"x":501,"y":62,"w":145,"h":56}},{"filename":"confetti/hexagon-0","rotated":false,"trimmed":true,"sourceSize":{"w":50,"h":50},"spriteSourceSize":{"x":0,"y":3,"w":50,"h":44},"frame":{"x":649,"y":62,"w":50,"h":44}},{"filename":"ribbon/falling-confetti/confetti-a/confetti-a-1","rotated":false,"trimmed":false,"sourceSize":{"w":21,"h":14},"spriteSourceSize":{"x":0,"y":0,"w":21,"h":14},"frame":{"x":649,"y":109,"w":21,"h":14}},{"filename":"ribbon/falling-confetti/confetti-d/confetti-d-1","rotated":false,"trimmed":false,"sourceSize":{"w":21,"h":14},"spriteSourceSize":{"x":0,"y":0,"w":21,"h":14},"frame":{"x":673,"y":109,"w":21,"h":14}},{"filename":"confetti/star-x/star-3","rotated":false,"trimmed":true,"sourceSize":{"w":21,"h":20},"spriteSourceSize":{"x":1,"y":4,"w":19,"h":12},"frame":{"x":697,"y":109,"w":19,"h":12}},{"filename":"star-x/star-3","rotated":false,"trimmed":true,"sourceSize":{"w":21,"h":20},"spriteSourceSize":{"x":1,"y":4,"w":19,"h":12},"frame":{"x":697,"y":109,"w":19,"h":12}},{"filename":"confetti/hexagon-4","rotated":false,"trimmed":true,"sourceSize":{"w":50,"h":50},"spriteSourceSize":{"x":5,"y":5,"w":41,"h":40},"frame":{"x":702,"y":62,"w":41,"h":40}},{"filename":"confetti/hexagon-1","rotated":false,"trimmed":true,"sourceSize":{"w":50,"h":50},"spriteSourceSize":{"x":2,"y":7,"w":48,"h":37},"frame":{"x":746,"y":2,"w":48,"h":37}},{"filename":"ribbon/falling-confetti/confetti-c/confetti-c-2","rotated":false,"trimmed":false,"sourceSize":{"w":25,"h":10},"spriteSourceSize":{"x":0,"y":0,"w":25,"h":10},"frame":{"x":725,"y":42,"w":25,"h":10}},{"filename":"confetti/hexagon-2","rotated":false,"trimmed":true,"sourceSize":{"w":50,"h":50},"spriteSourceSize":{"x":5,"y":9,"w":40,"h":33},"frame":{"x":753,"y":42,"w":40,"h":33}},{"filename":"ribbon/falling-confetti/confetti-b/confetti-b-2","rotated":false,"trimmed":false,"sourceSize":{"w":23,"h":9},"spriteSourceSize":{"x":0,"y":0,"w":23,"h":9},"frame":{"x":719,"y":105,"w":23,"h":9}},{"filename":"ribbon/falling-confetti/confetti-d/confetti-d-2","rotated":false,"trimmed":false,"sourceSize":{"w":23,"h":9},"spriteSourceSize":{"x":0,"y":0,"w":23,"h":9},"frame":{"x":719,"y":117,"w":23,"h":9}},{"filename":"ribbon/falling-confetti/confetti-a/confetti-a-2","rotated":false,"trimmed":false,"sourceSize":{"w":21,"h":7},"spriteSourceSize":{"x":0,"y":0,"w":21,"h":7},"frame":{"x":745,"y":105,"w":21,"h":7}},{"filename":"confetti/small-1","rotated":false,"trimmed":false,"sourceSize":{"w":26,"h":29},"spriteSourceSize":{"x":0,"y":0,"w":26,"h":29},"frame":{"x":769,"y":78,"w":26,"h":29}},{"filename":"confetti/star-x/star-4","rotated":false,"trimmed":true,"sourceSize":{"w":21,"h":20},"spriteSourceSize":{"x":1,"y":7,"w":19,"h":6},"frame":{"x":746,"y":78,"w":19,"h":6}},{"filename":"star-x/star-4","rotated":false,"trimmed":true,"sourceSize":{"w":21,"h":20},"spriteSourceSize":{"x":1,"y":7,"w":19,"h":6},"frame":{"x":746,"y":78,"w":19,"h":6}},{"filename":"ribbon/falling-confetti/confetti-d/confetti-d-3","rotated":false,"trimmed":false,"sourceSize":{"w":23,"h":6},"spriteSourceSize":{"x":0,"y":0,"w":23,"h":6},"frame":{"x":769,"y":110,"w":23,"h":6}},{"filename":"ribbon/falling-confetti/confetti-c/confetti-c-4","rotated":false,"trimmed":false,"sourceSize":{"w":22,"h":6},"spriteSourceSize":{"x":0,"y":0,"w":22,"h":6},"frame":{"x":745,"y":119,"w":22,"h":6}}]}],"meta":{"app":"https://www.codeandweb.com/texturepacker","version":"3.0","smartupdate":"$TexturePacker:SmartUpdate:bbf4861790794d3f52db0c14fde2b02b:5e83d725f800db11f411cd388bb32859:fcf0ca429d8c303c4783c89b34559bdb$"}}